Metadata-Version: 2.1
Name: odoo12-addon-storage-file
Version: 12.0.2.0.4
Summary: Storage file in storage backend
Home-page: https://github.com/OCA/storage
Author: Akretion, Odoo Community Association (OCA)
Author-email: support@odoo-community.org
License: AGPL-3
Platform: UNKNOWN
Classifier: Programming Language :: Python
Classifier: Framework :: Odoo
Classifier: Framework :: Odoo :: 12.0
Classifier: License :: OSI Approved :: GNU Affero General Public License v3
Classifier: Development Status :: 5 - Production/Stable
Requires-Python: >=3.5
Requires-Dist: odoo12-addon-storage-backend
Requires-Dist: odoo <12.1dev,>=12.0a
Requires-Dist: python-slugify >=3.0.2
